andersen/__init__.py
andersen/config.py
andersen/exception.py
andersen/log.py
andersen/logger_helper.py
src/__init__.py
src/test.py
src/andersen/__init__.py
src/andersen/exception.py
src/andersen/log.py
src/andersen/logger_helper.py
andersen-0.0.1.dist-info/METADATA
andersen-0.0.1.dist-info/WHEEL
andersen-0.0.1.dist-info/top_level.txt
andersen-0.0.1.dist-info/RECORD
