Metadata-Version: 2.1
Name: andersen
Version: 0.0.1
Summary: python log library
Home-page: https://gitee.com/happy3014/andersen
Author: idlefish
Author-email: lvhuanle12@126.com
Maintainer: idlefish
Maintainer-email: lvhuanle12@126.com
License: BSD License
Platform: all
Classifier: Development Status :: 4 - Beta
Classifier: Operating System :: OS Independent
Classifier: Intended Audience :: Developers
Classifier: License :: OSI Approved :: BSD License
Classifier: Programming Language :: Python
Classifier: Programming Language :: Python :: Implementation
Classifier: Programming Language :: Python :: 3.6
Classifier: Topic :: Software Development :: Libraries
Requires-Dist: toml
